logui/__init__.py
logui/apps.py
logui/conf.py
logui/middleware.py
logui/utils.py
logui/classes/__init__.py
logui/controllers/__init__.py
logui/controllers/base.py
logui/routes/__init__.py
logui/routes/views.py
logui/static/logui/css/bootstrap.min.css
logui/static/logui/css/highlight.min.css
logui/static/logui/css/wide-classes.css
logui/static/logui/js/Client.js
logui/static/logui/js/highlight.min.js
logui/templates/logui/base.html
logui/templates/logui/error_report.html
logui/templates/logui/log_file.html
logui/templates/logui/log_files.html
logui/templates/logui/log_folders.html
django_logui-0.1.2.dist-info/LICENSE
django_logui-0.1.2.dist-info/METADATA
django_logui-0.1.2.dist-info/WHEEL
django_logui-0.1.2.dist-info/top_level.txt
django_logui-0.1.2.dist-info/RECORD
