Metadata-Version: 2.1
Name: django-logui
Version: 0.1.2
Summary: Flexible, fast and productive UI for logging in Django
Home-page: https://github.com/Artasov/django-logui
Author: xlartas
Author-email: ivanhvalevskey@gmail.com
Project-URL: Source, https://github.com/Artasov/django-logui
Project-URL: Tracker, https://github.com/Artasov/django-logui/issues
Keywords: django-logui django utils funcs features logs logging logger
Classifier: Framework :: Django
Classifier: Framework :: Django :: 4.0
Classifier: Programming Language :: Python :: 3.8
Classifier: Programming Language :: Python :: 3.9
Classifier: Programming Language :: Python :: 3.10
Classifier: Programming Language :: Python :: 3.11
Classifier: Programming Language :: Python :: 3.12
Classifier: Operating System :: OS Independent
Classifier: License :: OSI Approved :: MIT License
Classifier: Intended Audience :: Developers
Classifier: Topic :: Software Development :: Libraries :: Application Frameworks
Requires-Python: >=3.8
License-File: LICENSE
Requires-Dist: Django<5.3,>=4.0
Requires-Dist: adjango>=0.2.8
